jsonmodels/__init__.py
jsonmodels/builders.py
jsonmodels/collections.py
jsonmodels/errors.py
jsonmodels/fields.py
jsonmodels/models.py
jsonmodels/parsers.py
jsonmodels/utilities.py
jsonmodels/validators.py
jsonmodels-2.8.0.dist-info/METADATA
jsonmodels-2.8.0.dist-info/WHEEL
jsonmodels-2.8.0.dist-info/licenses/AUTHORS.rst
jsonmodels-2.8.0.dist-info/licenses/LICENSE
jsonmodels-2.8.0.dist-info/RECORD
