Metadata-Version: 2.4
Name: jsonmodels
Version: 2.8.0
Summary: Models to make easier to deal with structures that are converted to, or read from JSON.
Project-URL: Home, https://github.com/jazzband/jsonmodels
Author-email: Szczepan Cieślik <szczepan.cieslik@gmail.com>
License: Copyright (c) 2014, Szczepan Cieślik
License-File: AUTHORS.rst
License-File: LICENSE
Classifier: Intended Audience :: Developers
Classifier: License :: OSI Approved :: BSD License
Classifier: Natural Language :: English
Classifier: Programming Language :: Python :: 3
Classifier: Programming Language :: Python :: 3 :: Only
Classifier: Programming Language :: Python :: 3.10
Classifier: Programming Language :: Python :: 3.11
Classifier: Programming Language :: Python :: 3.12
Classifier: Programming Language :: Python :: 3.13
Classifier: Programming Language :: Python :: 3.14
Requires-Python: >=3.10
Requires-Dist: python-dateutil
Provides-Extra: dev
Requires-Dist: coverage; extra == 'dev'
Requires-Dist: docutils; extra == 'dev'
Requires-Dist: flake8; extra == 'dev'
Requires-Dist: flake8-pyproject; extra == 'dev'
Requires-Dist: importlib-metadata==4.13.0; extra == 'dev'
Requires-Dist: invoke; extra == 'dev'
Requires-Dist: jinja2; extra == 'dev'
Requires-Dist: markupsafe; extra == 'dev'
Requires-Dist: mccabe; extra == 'dev'
Requires-Dist: pep8; extra == 'dev'
Requires-Dist: py; extra == 'dev'
Requires-Dist: pyflakes; extra == 'dev'
Requires-Dist: pygments; extra == 'dev'
Requires-Dist: pytest; extra == 'dev'
Requires-Dist: pytest-cov; extra == 'dev'
Requires-Dist: sphinx; extra == 'dev'
Requires-Dist: sphinxcontrib-spelling; extra == 'dev'
